runai/__init__.py
runai/api/__init__.py
runai/api/access_keys_api.py
runai/api/access_rules_api.py
runai/api/administrator_command_line_interface_api.py
runai/api/ai_applications_api.py
runai/api/applications_api.py
runai/api/audit_logs_api.py
runai/api/clusters_api.py
runai/api/compute_api.py
runai/api/config_map_api.py
runai/api/credentials_api.py
runai/api/datasources_api.py
runai/api/datavolumes_api.py
runai/api/departments_api.py
runai/api/distributed_api.py
runai/api/distributed_inferences_api.py
runai/api/environment_api.py
runai/api/events_api.py
runai/api/git_api.py
runai/api/host_path_api.py
runai/api/idps_api.py
runai/api/inferences_api.py
runai/api/logo_api.py
runai/api/me_api.py
runai/api/network_topologies_api.py
runai/api/nfs_api.py
runai/api/node_pools_api.py
runai/api/nodes_api.py
runai/api/notification_channels_api.py
runai/api/notification_state_api.py
runai/api/notification_types_api.py
runai/api/nvidianim_api.py
runai/api/org_unit_api.py
runai/api/permissions_api.py
runai/api/pods_api.py
runai/api/policy_api.py
runai/api/projects_api.py
runai/api/pvc_api.py
runai/api/registry_api.py
runai/api/reports_api.py
runai/api/researcher_command_line_interface_api.py
runai/api/researcher_command_line_interface_deprecated_api.py
runai/api/revisions_api.py
runai/api/roles_api.py
runai/api/runai_api_service.py
runai/api/s3_api.py
runai/api/secret_api.py
runai/api/service_accounts_api.py
runai/api/settings_api.py
runai/api/storage_class_configuration_api.py
runai/api/storage_classes_api.py
runai/api/subscriptions_api.py
runai/api/template_api.py
runai/api/tenant_api.py
runai/api/tokens_api.py
runai/api/trainings_api.py
runai/api/user_applications_api.py
runai/api/users_api.py
runai/api/workload_properties_api.py
runai/api/workload_templates_api.py
runai/api/workloads_api.py
runai/api/workloads_batch_api.py
runai/api/workloads_v2_api.py
runai/api/workspaces_api.py
runai/api_client.py
runai/api_response.py
runai/async_rest.py
runai/cliv2_config_loader.py
runapy-1.224.0.dist-info/METADATA
runapy-1.224.0.dist-info/WHEEL
runapy-1.224.0.dist-info/licenses/LICENSE
runapy-1.224.0.dist-info/RECORD
