Metadata-Version: 2.4
Name: runapy
Version: 1.224.0
Summary: Python client for Run:ai REST API
License: Apache-2
License-File: LICENSE
Keywords: runai,kubernetes,gpu,orchestration
Author: Run:ai Professional Services Team
Requires-Python: >=3.8,<4.0
Classifier: License :: Other/Proprietary License
Classifier: Programming Language :: Python :: 3
Classifier: Programming Language :: Python :: 3.8
Classifier: Programming Language :: Python :: 3.9
Classifier: Programming Language :: Python :: 3.10
Classifier: Programming Language :: Python :: 3.11
Classifier: Programming Language :: Python :: 3.12
Classifier: Programming Language :: Python :: 3.13
Classifier: Programming Language :: Python :: 3.14
Requires-Dist: aiohttp (>=3.8.5)
Requires-Dist: aiohttp-retry (>=2.9.1)
Requires-Dist: pydantic (>=2)
Requires-Dist: python-dateutil (>=2.8.2)
Requires-Dist: typing-extensions (>=4.7.1)
Requires-Dist: urllib3 (>=1.25.3,<3.0.0)
Project-URL: Homepage, https://github.com/runai-professional-services/runapy
Project-URL: Repository, https://github.com/runai-professional-services/runapy
